[{"title":"Vitamin Korean 1.pdf","tags":[],"link":"vitaminkorean1pdf.pdf","size":27322822},{"title":"Vitamin Korean 1 MP3.zip","tags":[],"link":"vitaminkorean1mp3zip.zip","size":44375356},{"title":"pdf-vitamin-korean-2_compress.pdf","tags":[],"link":"pdf-vitamin-korean-2compresspdf.pdf","size":20543331},{"title":"Vitamin Korean 2 MP3.zip","tags":[],"link":"vitaminkorean2mp3zip.zip","size":40251849},{"title":"Vitamin Korean 3.pdf","tags":[],"link":"vitaminkorean3pdf.pdf","size":33099589},{"title":"Vitamin Korean 3 MP3 Part 1.zip","tags":[],"link":"vitaminkorean3mp3part1zip.zip","size":36697128},{"title":"Vitamin Korean 3 MP3 Part 2.zip","tags":[],"link":"vitaminkorean3mp3part2zip.zip","size":28503353},{"title":"Vitamin Korean 4.pdf","tags":[],"link":"vitaminkorean4pdf.pdf","size":31273877},{"title":"Vitamin Korean 4 MP3 Part 1.zip","tags":[],"link":"vitaminkorean4mp3part1zip.zip","size":33104306},{"title":"Vitamin Korean 4 MP3 Part 2.zip","tags":[],"link":"vitaminkorean4mp3part2zip.zip","size":31410227},{"title":"Vitamin Korean 5.pdf","tags":[],"link":"vitaminkorean5pdf.pdf","size":36811490},{"title":"Vitamin Korean 5 MP3.zip","tags":[],"link":"vitaminkorean5mp3zip.zip","size":53616830},{"title":"Vitamin Korean 6.pdf","tags":[],"link":"vitaminkorean6pdf.pdf","size":36688841},{"title":"Vitamin Korean 6 MP3.zip","tags":[],"link":"vitaminkorean6mp3zip.zip","size":56642160}]